dotprompt/__init__.py
dotprompt/exceptions.py
dotprompt/prompt.py
dotprompt-0.1.10.dist-info/LICENSE
dotprompt-0.1.10.dist-info/METADATA
dotprompt-0.1.10.dist-info/WHEEL
dotprompt-0.1.10.dist-info/top_level.txt
dotprompt-0.1.10.dist-info/RECORD
